Metadata-Version: 2.1
Name: minicrypt
Version: 1.0
Summary: Easy encryption algorithm
Home-page: UNKNOWN
Author-email: cklfgads@knowledgemd.com
License: UNKNOWN
Platform: UNKNOWN
